LICENSE
MANIFEST.in
README.rst
setup.cfg
setup.py
pynblock/__init__.py
pynblock/tests.py
pynblock/tools.py
pynblock.egg-info/PKG-INFO
pynblock.egg-info/SOURCES.txt
pynblock.egg-info/dependency_links.txt
pynblock.egg-info/requires.txt
pynblock.egg-info/top_level.txt
pynblock.egg-info/zip-safe