Metadata-Version: 1.1
Name: pynblock
Version: 0.24
Summary: Payment card industry crypto library - PIN blocks, card/PIN verification values calculation etc.
Home-page: https://github.com/timgabets/pynblock
Author: Tim Gabets
Author-email: tim@gabets.ru
License: LGPLv2
Keywords: payment crypto card pin cvv csc pinblock
Platform: UNKNOWN
Classifier: License :: OSI Approved :: GNU Lesser General Public License v2 (LGPLv2)
Classifier: Operating System :: OS Independent
Classifier: Programming Language :: Python :: 2
Classifier: Programming Language :: Python :: 2.7
Classifier: Programming Language :: Python :: 3
Classifier: Programming Language :: Python :: 3.3
Classifier: Programming Language :: Python :: 3.4
Classifier: Programming Language :: Python :: 3.5
Classifier: Topic :: Communications
Classifier: Intended Audience :: Developers
